odoo8_addon_crm_lead_vat-8.0.1.1.1-py2.7-nspkg.pth
odoo8_addon_crm_lead_vat-8.0.1.1.1.dist-info/DESCRIPTION.rst
odoo8_addon_crm_lead_vat-8.0.1.1.1.dist-info/METADATA
odoo8_addon_crm_lead_vat-8.0.1.1.1.dist-info/RECORD
odoo8_addon_crm_lead_vat-8.0.1.1.1.dist-info/WHEEL
odoo8_addon_crm_lead_vat-8.0.1.1.1.dist-info/metadata.json
odoo8_addon_crm_lead_vat-8.0.1.1.1.dist-info/namespace_packages.txt
odoo8_addon_crm_lead_vat-8.0.1.1.1.dist-info/top_level.txt
odoo_addons/crm_lead_vat/README.rst
odoo_addons/crm_lead_vat/__init__.py
odoo_addons/crm_lead_vat/__openerp__.py
odoo_addons/crm_lead_vat/models.py
odoo_addons/crm_lead_vat/i18n/bg.po
odoo_addons/crm_lead_vat/i18n/crm_lead_vat.pot
odoo_addons/crm_lead_vat/i18n/de.po
odoo_addons/crm_lead_vat/i18n/es.po
odoo_addons/crm_lead_vat/i18n/fr.po
odoo_addons/crm_lead_vat/i18n/hr.po
odoo_addons/crm_lead_vat/i18n/it.po
odoo_addons/crm_lead_vat/i18n/pt_BR.po
odoo_addons/crm_lead_vat/i18n/sk.po
odoo_addons/crm_lead_vat/i18n/sl.po
odoo_addons/crm_lead_vat/i18n/zh_CN.po
odoo_addons/crm_lead_vat/static/description/icon.png
odoo_addons/crm_lead_vat/tests/__init__.py
odoo_addons/crm_lead_vat/tests/test_lead.py
odoo_addons/crm_lead_vat/views/crm_lead.xml
